field_commons/__init__.py
field_commons/events_util/__init__.py
field_commons/events_util/threadedevents.py
field_commons/keycloak_util/__init__.py
field_commons/mongo_util/__init__.py
domino_field_commons-1.0.3.dist-info/LICENSE
domino_field_commons-1.0.3.dist-info/METADATA
domino_field_commons-1.0.3.dist-info/WHEEL
domino_field_commons-1.0.3.dist-info/top_level.txt
domino_field_commons-1.0.3.dist-info/RECORD
