Metadata-Version: 2.1
Name: domino_field_commons
Version: 1.0.3
Summary: Library of common APIs used by field deployed code
Author: Field Engineering
Requires-Python: >=3.9.1
License-File: LICENSE
